celery_client_stubs/__init__.py
celery_client_stubs-0.7.1.dist-info/LICENSE
celery_client_stubs-0.7.1.dist-info/METADATA
celery_client_stubs-0.7.1.dist-info/WHEEL
celery_client_stubs-0.7.1.dist-info/top_level.txt
celery_client_stubs-0.7.1.dist-info/RECORD
