Metadata-Version: 2.1
Name: celery-client-stubs
Version: 0.7.1
Summary: Client-side stubs for celery task execution
Home-page: https://github.com/carstencodes/celery_client_stubs
Author: Carsten Igel
Author-email: cig@bite-that-bit.de
License: BSD 3-Clause
Platform: UNKNOWN
Classifier: Development Status :: 4 - Beta
Classifier: License :: OSI Approved :: BSD License
Classifier: Intended Audience :: Developers
Classifier: Operating System :: OS Independent
Classifier: Programming Language :: Python :: 3.7
Classifier: Programming Language :: Python :: 3.8
Classifier: Programming Language :: Python :: 3.9
Classifier: Topic :: Software Development :: Libraries :: Python Modules
Classifier: Topic :: System
Classifier: Typing :: Typed
Requires-Python: >=3.7, < 4
Requires-Dist: celery (>=5.0)
